py2dash/__init__.py
py2dash/app_makers.py
py2dash/component_makers.py
py2dash/converters.py
py2dash/dash01.py
py2dash/dash99.py
py2dash/dash_introspection.py
py2dash/dashmint.py
py2dash/errors.py
py2dash/misc.py
py2dash/util.py
py2dash/conventions/__init__.py
py2dash/examples/__init__.py
py2dash/examples/classification_confusion.py
py2dash/examples/graph_viz.py
py2dash/examples/probability_of_failure.py
py2dash/examples/really_dynamic_layout.py
py2dash/examples/sklearn_estimators.py
py2dash/examples/with_py_simple_guid.py
py2dash/scrap/__init__.py
py2dash/scrap/dash01.py
py2dash/scrap/dash02.py
py2dash/scrap/dash03.py
py2dash/scrap/dash98.py
py2dash/scrap/dynamic_callbacks_and_layouts.py
py2dash/scrap/dynamic_layout.py
py2dash/scrap/multiple_inputs_graph_output.py
py2dash-0.0.2.dist-info/LICENSE
py2dash-0.0.2.dist-info/METADATA
py2dash-0.0.2.dist-info/WHEEL
py2dash-0.0.2.dist-info/top_level.txt
py2dash-0.0.2.dist-info/RECORD
