Metadata-Version: 2.1
Name: py2dash
Version: 0.0.2
Summary: Tools to produce dash (plot.ly) interfaces from existing python functionality
Home-page: https://github.com/i2mint/py2dash
Author: Thor Whalen
Author-email: UNKNOWN
License: Apache
Platform: any
Requires-Dist: flask
Requires-Dist: dash
Requires-Dist: argh
